csvstats1/Cool.py
csvstats1/__init__.py
csvTofile-0.1.dist-info/METADATA
csvTofile-0.1.dist-info/WHEEL
csvTofile-0.1.dist-info/top_level.txt
csvTofile-0.1.dist-info/RECORD
